xcavation/__init__.py
xcavation/aperture.py
xcavation/genspec.py
xcavation/motion.py
xcavation/psf.py
xcavation/quality.py
xcavation-0.1.0.dist-info/licenses/LICENSE
xcavation-0.1.0.dist-info/METADATA
xcavation-0.1.0.dist-info/WHEEL
xcavation-0.1.0.dist-info/top_level.txt
xcavation-0.1.0.dist-info/RECORD
