Metadata-Version: 2.4
Name: xcavation
Version: 0.1.0
Summary: SphereX Data Retrieval and Photometry Toolkit
Home-page: https://github.com/huntbrooks85/xcavation
Author: Hunter Brooks
Author-email: hbrooks8@rockets.utoledo.edu
License: MIT License
Classifier: Programming Language :: Python :: 3
Classifier: License :: OSI Approved :: MIT License
Classifier: Operating System :: OS Independent
Requires-Python: >=3.10
License-File: LICENSE
Requires-Dist: numpy
Requires-Dist: scipy
Requires-Dist: pandas
Requires-Dist: matplotlib
Requires-Dist: astropy
Requires-Dist: astroquery
Requires-Dist: photutils
Requires-Dist: scikit-learn
Requires-Dist: xarray
Requires-Dist: tqdm
Requires-Dist: h5py
Requires-Dist: emcee
Requires-Dist: corner
Requires-Dist: pathos
Requires-Dist: requests
Dynamic: author
Dynamic: author-email
Dynamic: classifier
Dynamic: description
Dynamic: description-content-type
Dynamic: home-page
Dynamic: license
Dynamic: license-file
Dynamic: requires-dist
Dynamic: requires-python
Dynamic: summary
